copier/__init__.py
copier/__main__.py
copier/_cli.py
copier/_deprecation.py
copier/_jinja_ext.py
copier/_main.py
copier/_subproject.py
copier/_template.py
copier/_tools.py
copier/_types.py
copier/_user_data.py
copier/_vcs.py
copier/cli.py
copier/errors.py
copier/jinja_ext.py
copier/main.py
copier/py.typed
copier/settings.py
copier/subproject.py
copier/template.py
copier/tools.py
copier/types.py
copier/user_data.py
copier/vcs.py
copier-9.11.3.dist-info/METADATA
copier-9.11.3.dist-info/WHEEL
copier-9.11.3.dist-info/entry_points.txt
copier-9.11.3.dist-info/licenses/LICENSE
copier-9.11.3.dist-info/RECORD
