Metadata-Version: 2.4
Name: copier
Version: 9.11.3
Summary: A library for rendering project templates.
Project-URL: homepage, https://github.com/copier-org/copier
Project-URL: repository, https://github.com/copier-org/copier
Project-URL: Bug Tracker, https://github.com/copier-org/copier/issues
Author-email: Ben Felder <ben@felder.io>
License: MIT
License-File: LICENSE
Classifier: Development Status :: 5 - Production/Stable
Classifier: Intended Audience :: Developers
Classifier: License :: OSI Approved :: MIT License
Classifier: Programming Language :: Python :: 3
Classifier: Programming Language :: Python :: 3.10
Classifier: Programming Language :: Python :: 3.11
Classifier: Programming Language :: Python :: 3.12
Classifier: Programming Language :: Python :: 3.13
Classifier: Programming Language :: Python :: 3.14
Requires-Python: >=3.10
Requires-Dist: colorama>=0.4.6
Requires-Dist: dunamai>=1.7.0
Requires-Dist: funcy>=1.17
Requires-Dist: jinja2-ansible-filters>=1.3.1
Requires-Dist: jinja2>=3.1.5
Requires-Dist: packaging>=23.0
Requires-Dist: pathspec>=0.9.0
Requires-Dist: platformdirs>=4.3.6
Requires-Dist: plumbum>=1.6.9
Requires-Dist: pydantic>=2.4.2
Requires-Dist: pygments>=2.7.1
Requires-Dist: pyyaml>=5.3.1
Requires-Dist: questionary>=1.8.1
Requires-Dist: typing-extensions<5.0.0,>=4.0.0; python_version < '3.11'
